MANIFEST.in
ez_setup.py
setup.py
barrelhouse/__init__.py
barrelhouse.egg-info/PKG-INFO
barrelhouse.egg-info/SOURCES.txt
barrelhouse.egg-info/dependency_links.txt
barrelhouse.egg-info/requires.txt
barrelhouse.egg-info/top_level.txt
barrelhouse/conf/__init__.py
barrelhouse/conf/global_settings.py
demo/config.py
demo/main.py
demo/main_gae.py
demo/assets/jquery.openid.js
demo/assets/openid.css
demo/assets/styles.css
demo/lib/settings/__init__.py
demo/lib/settings/barrelhouse.py
demo/lib/settings/djinn.py
demo/templates/base.html
demo/templates/form_openid.html
demo/templates/form_username_password.html
demo/templates/index.html
demo/templates/signin.html