Metadata-Version: 1.0
Name: barrelhouse
Version: 0.3
Summary: WSGI OpenID authentication handler
Home-page: http://bitbucket.org/walterwefft/barrelhouse
Author: Walter Wefft
Author-email: walterwefft@gmail.com
License: BSD
Download-URL: http://pypi.python.org/packages/source/b/barrelhouse/barrelhouse-0.3.tar.gz
Platform: UNKNOWN
Classifier: Development Status :: 1 - Planning
Classifier: Intended Audience :: Developers
Classifier: License :: OSI Approved :: BSD License
Classifier: Programming Language :: Python
Classifier: Environment :: Web Environment
Classifier: Topic :: Internet :: WWW/HTTP :: WSGI
Classifier: Topic :: Internet :: WWW/HTTP :: WSGI :: Middleware
